Metadata-Version: 1.0
Name: merge-effort
Version: 1.1.0
Summary: a script to measure merge effort
Home-page: https://github.com/gems-uff/merge-effort
Author: Tayane Moura and Leonardo Murta
Author-email: tayanemoura@id.uff.br
License: MIT
Platform: UNKNOWN
